setup.py
aberquota/__init__.py
aberquota/aberquota.py
aberquota.egg-info/PKG-INFO
aberquota.egg-info/SOURCES.txt
aberquota.egg-info/dependency_links.txt
aberquota.egg-info/not-zip-safe
aberquota.egg-info/requires.txt
aberquota.egg-info/top_level.txt
bin/aberquota