Metadata-Version: 1.1
Name: aberquota
Version: 1.1
Summary: Python3 tool for getting internet usage off the Aberystwyth University network
Home-page: https://github.com/Jafnee/aberquota
Author: Jafnee Jesmee
Author-email: jafneejesmee@gmail.com
License: UNKNOWN
Platform: UNKNOWN
Classifier: Development Status :: 3 - Alpha
Classifier: Programming Language :: Python :: 3 :: Only
